py3dtiles/__init__.py
py3dtiles/command_line.py
py3dtiles/constants.py
py3dtiles/convert.py
py3dtiles/exceptions.py
py3dtiles/export.py
py3dtiles/info.py
py3dtiles/merger.py
py3dtiles/points.py
py3dtiles/py.typed
py3dtiles/typing.py
py3dtiles/utils.py
py3dtiles/reader/__init__.py
py3dtiles/reader/las_reader.py
py3dtiles/reader/ply_reader.py
py3dtiles/reader/xyz_reader.py
py3dtiles/tilers/__init__.py
py3dtiles/tilers/shared_store.py
py3dtiles/tilers/b3dm/__init__.py
py3dtiles/tilers/b3dm/wkb_utils.py
py3dtiles/tilers/base_tiler/__init__.py
py3dtiles/tilers/base_tiler/message_type.py
py3dtiles/tilers/base_tiler/shared_metadata.py
py3dtiles/tilers/base_tiler/tiler.py
py3dtiles/tilers/base_tiler/tiler_worker.py
py3dtiles/tilers/ifc/__init__.py
py3dtiles/tilers/ifc/ifc_exceptions.py
py3dtiles/tilers/ifc/ifc_message_type.py
py3dtiles/tilers/ifc/ifc_model.py
py3dtiles/tilers/ifc/ifc_shared_metadata.py
py3dtiles/tilers/ifc/ifc_tiler.py
py3dtiles/tilers/ifc/ifc_tiler_worker.py
py3dtiles/tilers/point/__init__.py
py3dtiles/tilers/point/matrix_manipulation.py
py3dtiles/tilers/point/point_message_type.py
py3dtiles/tilers/point/point_shared_metadata.py
py3dtiles/tilers/point/point_state.py
py3dtiles/tilers/point/point_tiler.py
py3dtiles/tilers/point/point_tiler_worker.py
py3dtiles/tilers/point/node/__init__.py
py3dtiles/tilers/point/node/distance.py
py3dtiles/tilers/point/node/node.py
py3dtiles/tilers/point/node/node_catalog.py
py3dtiles/tilers/point/node/node_process.py
py3dtiles/tilers/point/node/points_grid.py
py3dtiles/tilers/point/pnts/__init__.py
py3dtiles/tilers/point/pnts/constants.py
py3dtiles/tilers/point/pnts/pnts_writer.py
py3dtiles/tileset/__init__.py
py3dtiles/tileset/bounding_volume.py
py3dtiles/tileset/bounding_volume_box.py
py3dtiles/tileset/root_property.py
py3dtiles/tileset/tile.py
py3dtiles/tileset/tileset.py
py3dtiles/tileset/utils.py
py3dtiles/tileset/content/__init__.py
py3dtiles/tileset/content/b3dm.py
py3dtiles/tileset/content/b3dm_feature_table.py
py3dtiles-12.0.0.dist-info/licenses/LICENSE
py3dtiles-12.0.0.dist-info/METADATA
py3dtiles-12.0.0.dist-info/WHEEL
py3dtiles-12.0.0.dist-info/entry_points.txt
py3dtiles-12.0.0.dist-info/top_level.txt
py3dtiles-12.0.0.dist-info/RECORD
