Metadata-Version: 2.4
Name: py3dtiles
Version: 12.0.0
Summary: Python module for 3D tiles format
Author-email: The Py3DTiles team <contact@oslandia.com>
License: Apache-2.0
Project-URL: Homepage, https://py3dtiles.org
Project-URL: Documentation, https://py3dtiles.org
Project-URL: Repository, https://gitlab.com/py3dtiles/py3dtiles
Project-URL: Issues, https://gitlab.com/py3dtiles/py3dtiles/-/issues
Project-URL: Changelog, https://gitlab.com/py3dtiles/py3dtiles/-/blob/main/CHANGELOG.md
Classifier: Development Status :: 3 - Alpha
Classifier: Intended Audience :: Developers
Classifier: Programming Language :: Python :: 3.10
Classifier: Programming Language :: Python :: 3.11
Classifier: Programming Language :: Python :: 3.12
Classifier: Programming Language :: Python :: 3.13
Requires-Python: <3.14,>=3.10
License-File: LICENSE
Requires-Dist: mapbox_earcut==1.0.3
Requires-Dist: lz4
Requires-Dist: numba<0.62.0,>=0.59
Requires-Dist: numpy<2.2.0,>=1.24.0
Requires-Dist: psutil
Requires-Dist: pyproj
Requires-Dist: pyzmq<26.4.0
Requires-Dist: pygltflib
Provides-Extra: postgres
Requires-Dist: psycopg2-binary; extra == "postgres"
Provides-Extra: las
Requires-Dist: laspy<3.0,>=2.5; extra == "las"
Provides-Extra: ply
Requires-Dist: plyfile; extra == "ply"
Provides-Extra: ifc
Requires-Dist: ifcopenshell; extra == "ifc"
Requires-Dist: lark; extra == "ifc"
Provides-Extra: dev
Requires-Dist: line_profiler; extra == "dev"
Requires-Dist: pre-commit; extra == "dev"
Requires-Dist: pytest>=8.4.0; extra == "dev"
Requires-Dist: pytest-benchmark; extra == "dev"
Requires-Dist: pytest-cov; extra == "dev"
Requires-Dist: mypy>=1.19.0; extra == "dev"
Requires-Dist: typing_extensions; extra == "dev"
Requires-Dist: types_psutil; extra == "dev"
Requires-Dist: types_psycopg2; extra == "dev"
Provides-Extra: doc
Requires-Dist: sphinx; extra == "doc"
Requires-Dist: sphinx-multiversion; extra == "doc"
Requires-Dist: sphinxcontrib-apidoc; extra == "doc"
Requires-Dist: pydata-sphinx-theme; extra == "doc"
Requires-Dist: myst-parser; extra == "doc"
Provides-Extra: pack
Requires-Dist: commitizen; extra == "pack"
Requires-Dist: build; extra == "pack"
Requires-Dist: twine; extra == "pack"
Requires-Dist: wheel; extra == "pack"
Dynamic: license-file
